LICENSE.txt
MANIFEST.in
README.txt
setup.py
django_portlets.egg-info/PKG-INFO
django_portlets.egg-info/SOURCES.txt
django_portlets.egg-info/dependency_links.txt
django_portlets.egg-info/not-zip-safe
django_portlets.egg-info/requires.txt
django_portlets.egg-info/top_level.txt
portlets/__init__.py
portlets/admin.py
portlets/apps.py
portlets/base.py
portlets/models.py
portlets/tests.py
portlets/utils.py
portlets/example/__init__.py
portlets/example/admin.py
portlets/example/models.py
portlets/example/templates/flatpages/default.html
portlets/example/templates/portlets/text_portlet.html
portlets/migrations/0001_initial.py
portlets/migrations/__init__.py
portlets/templates/portlets/portlet_slot.html
portlets/templatetags/__init__.py
portlets/templatetags/portlets_tags.py